{"name":"源思弦","data":[{"Name":"咒凌爆发","MinRadius":"0","MaxRadius":["100"],"Height":"100","AngleRange":"256","AreaRadius":"40","TargetCountLimit":["-1"],"DamageBase":["22600","28700","32200","4","0","0","0","0","0","0"],"SkillBaseInfo":{"IdKey":16976,"SkillID":22510,"IconID":13,"Level":0,"Name":"咒凌爆发","Desc":"测试技能","Remark":"(22510) 4号_咒凌读条","SpecialDesc":null,"HelpDesc":null,"IsHotkeyExitWhenForget":null,"SimpleDesc":null}},{"Name":"岚吟","AngleRange":"128","AreaRadius":"30","TargetCountLimit":["-1"],"PrepareFrames":["32"],"BrokenRate":"0","BeatBackRate":"0","DamageBase":["22600","45900","44100","400","0","0","0","0","0","0"],"SkillBaseInfo":{"IdKey":16882,"SkillID":22365,"IconID":13,"Level":0,"Name":"禊祓岚吟","Desc":"测试技能","Remark":"(22365) 4号_禊祓岚吟","SpecialDesc":null,"HelpDesc":null,"IsHotkeyExitWhenForget":null,"SimpleDesc":null}},{"Name":"BOSS内功普攻","MinRadius":"0","MaxRadius":["10"],"DamageBase":["34700","49700","22400","400","0","0","0","0","0","0"],"SkillBaseInfo":{"IdKey":16853,"SkillID":22324,"IconID":13,"Level":0,"Name":"扇落","Desc":"测试技能","Remark":"(22324) 4号_BOSS内功普攻","SpecialDesc":null,"HelpDesc":null,"IsHotkeyExitWhenForget":null,"SimpleDesc":null}},{"Name":"传染间隔BUFF","SkillBaseInfo":{"IconID":316}},{"Name":"BOSS外功普攻","MinRadius":"0","MaxRadius":["10"],"DamageBase":["33400","49700","112000","400","0","0","0","0","0","0"],"SkillBaseInfo":{"IdKey":16852,"SkillID":22323,"IconID":13,"Level":0,"Name":"扇起","Desc":"测试技能","Remark":"(22323) 4号_BOSS外功普攻","SpecialDesc":null,"HelpDesc":null,"IsHotkeyExitWhenForget":null,"SimpleDesc":null}},{"Name":"下P监控","SkillBaseInfo":{"IconID":316}},{"Name":"传送读条","PrepareFrames":["16","24","32"],"BrokenRate":"0","BeatBackRate":"0","DamageBase":["0","0","0","0","0","0","0","0","0","0"],"SkillBaseInfo":{"IdKey":16905,"SkillID":22392,"IconID":13,"Level":0,"Name":"异域位移","Desc":"测试技能","Remark":"(22392) 4号_传送读条","SpecialDesc":null,"HelpDesc":null,"IsHotkeyExitWhenForget":null,"SimpleDesc":null}},{"Name":"冰霜结界","SkillBaseInfo":{"IconID":316}},{"Name":"冲刺结束放技能","SkillBaseInfo":{"IconID":316}},{"Name":"冰霜矩形AOE","MinRadius":"0","MaxRadius":["100"],"Height":"40","RectWidth":"5","AngleRange":"256","AreaRadius":"40","TargetCountLimit":["-1"],"PrepareFrames":["48"],"BrokenRate":"0","BeatBackRate":"0","DamageBase":["29000","47600","61600","0","0","0","0","0","0","0"],"SkillBaseInfo":{"IdKey":16883,"SkillID":22367,"IconID":13,"Level":0,"Name":"禊祓·绀凌","Desc":"测试技能","Remark":"(22367) 4号_冰霜矩形AOE","SpecialDesc":null,"HelpDesc":null,"IsHotkeyExitWhenForget":null,"SimpleDesc":null}},{"Name":"反向嘲讽","BindBuff":["15604"],"MinRadius":"0","MaxRadius":["100"],"AngleRange":"256","DamageBase":["0"],"BindBuffDetail":[{"IdKey":13651,"BuffID":15604,"IconID":3417,"Level":1,"Name":"护主心切","Desc":"为了保护主人，攻击源思弦的当前目标","Remark":"(15604)(1)4号_式神强制攻击"}],"SkillBaseInfo":{"IdKey":15596,"SkillID":20449,"IconID":13,"Level":0,"Name":null,"Desc":"反向嘲讽","Remark":"(20449) 韩清芒_反向嘲讽","SpecialDesc":"反向嘲讽","HelpDesc":null,"IsHotkeyExitWhenForget":null,"SimpleDesc":null}},{"Name":"召唤黑洞读条","PrepareFrames":["32","96"],"BrokenRate":"0","BeatBackRate":"0","DamageBase":["0","0","0","0","0","0","0","0","0","0"],"SkillBaseInfo":{"IdKey":16939,"SkillID":22449,"IconID":13,"Level":1,"Name":"天地剧变","Desc":"测试技能","Remark":"(22449) 4号_召唤黑洞读条","SpecialDesc":null,"HelpDesc":null,"IsHotkeyExitWhenForget":null,"SimpleDesc":null}},{"Name":"咒凌爆发_小范围","MinRadius":"0","MaxRadius":["100"],"Height":"40","AngleRange":"256","AreaRadius":"8","TargetCountLimit":["-1"],"DamageBase":["14100","20500","23000","4","0","0","0","0","0","0"],"SkillBaseInfo":{"IconID":316}},{"Name":"小式神外功普攻","MinRadius":"0","MaxRadius":["10"],"DamageBase":["29500","12000","22400","400","0","0","0","0","0","0"],"SkillBaseInfo":{"IdKey":17320,"SkillID":23002,"IconID":13,"Level":0,"Name":"咬噬","Desc":"测试技能","Remark":"(23002) 4号_小式神外功普攻","SpecialDesc":null,"HelpDesc":null,"IsHotkeyExitWhenForget":null,"SimpleDesc":null}},{"Name":"回收小怪","MinRadius":"0","MaxRadius":["100"],"Height":"100","AngleRange":"256","AreaRadius":"1000","TargetCountLimit":["-1"],"DamageBase":["0","0","0","0","0","0","0","0","0","0"],"SkillBaseInfo":{"IconID":316}},{"Name":"岚吟读条","PrepareFrames":["92","240","44"],"BrokenRate":"0","BeatBackRate":"0","DamageBase":["0","0","0","0","0","0","0","0","0","0"],"SkillBaseInfo":{"IdKey":16901,"SkillID":22389,"IconID":13,"Level":1,"Name":"岚吟","Desc":"测试技能","Remark":"(22389) 4号_岚吟读条","SpecialDesc":null,"HelpDesc":null,"IsHotkeyExitWhenForget":null,"SimpleDesc":null}},{"Name":"咒凌爆发读条","PrepareFrames":["24"],"BrokenRate":"0","BeatBackRate":"0","DamageBase":["0","0","0","0","0","0","0","0","0","0"],"SkillBaseInfo":{"IconID":316}},{"Name":"咒凌爆发子技能","MinRadius":"0","MaxRadius":["100"],"Height":"20","AngleRange":"256","AreaRadius":"40","TargetCountLimit":["3","5","7","1","2","3"],"DamageBase":["1","2","3","4","0","0","0","0","0","0"],"SkillBaseInfo":{"IconID":316}},{"Name":"小式神普攻母技能","MinRadius":"0","MaxRadius":["4"],"DamageBase":["0","0","0","0","0","0","0","0","0","0"],"SkillBaseInfo":{"IconID":316}},{"Name":"巫力盈溢伤害","MinRadius":"0","MaxRadius":["100"],"Height":"20","AngleRange":"256","AreaRadius":"20","TargetCountLimit":["-1"],"DamageBase":["1","2","3","4","0","0","0","0","0","0"],"SkillBaseInfo":{"IdKey":16819,"SkillID":22286,"IconID":13,"Level":0,"Name":"巫力盈溢","Desc":"测试技能","Remark":"(22286) 4号_巫力盈溢伤害","SpecialDesc":null,"HelpDesc":null,"IsHotkeyExitWhenForget":null,"SimpleDesc":null}},{"Name":"巫力爆发吟唱","PrepareFrames":["64"],"BrokenRate":"0","BeatBackRate":"0","DamageBase":["0","0","0","0","0","0","0","0","0","0"],"SkillBaseInfo":{"IconID":316}},{"Name":"式神攻击尹青羲技能","MinRadius":"0","MaxRadius":["5"],"AngleRange":"256","DamageBase":["21450","35100","40950","400","0","0","0","0","0","0"],"SkillBaseInfo":{"IdKey":17072,"SkillID":22618,"IconID":13,"Level":0,"Name":"咬噬","Desc":"测试技能","Remark":"(22618) 4号_式神攻击尹青羲技能","SpecialDesc":null,"HelpDesc":null,"IsHotkeyExitWhenForget":null,"SimpleDesc":null}},{"Name":"式神内功普攻","MinRadius":"0","MaxRadius":["10"],"DamageBase":["33400","12000","22400","400","0","0","0","0","0","0"],"SkillBaseInfo":{"IdKey":16870,"SkillID":22347,"IconID":13,"Level":0,"Name":"咬噬","Desc":"测试技能","Remark":"(22347) 4号_式神内功普攻","SpecialDesc":null,"HelpDesc":null,"IsHotkeyExitWhenForget":null,"SimpleDesc":null}},{"Name":"式神外功普攻","MinRadius":"0","MaxRadius":["10"],"DamageBase":["33400","48000","105600","400","0","0","0","0","0","0"],"SkillBaseInfo":{"IdKey":16869,"SkillID":22346,"IconID":13,"Level":0,"Name":"咬噬","Desc":"测试技能","Remark":"(22346) 4号_式神外功普攻","SpecialDesc":null,"HelpDesc":null,"IsHotkeyExitWhenForget":null,"SimpleDesc":null}},{"Name":"护主心切飞扑","MinRadius":"0","MaxRadius":["100"],"AngleRange":"256","AreaRadius":"100","TargetCountLimit":["5"],"DamageBase":["0","0","0","0","0","0","0","0","0","0"],"SkillBaseInfo":{"IconID":316}},{"Name":"护主心切","PrepareFrames":["48","40","32","16","16"],"BrokenRate":"1024","BeatBackRate":"0","DamageBase":["0","0","0","0","0","0","0","0","0","0"],"SkillBaseInfo":{"IdKey":16871,"SkillID":22348,"IconID":13,"Level":0,"Name":"护主","Desc":"测试技能","Remark":"(22348) 4号_护主心切","SpecialDesc":null,"HelpDesc":null,"IsHotkeyExitWhenForget":null,"SimpleDesc":null}},{"Name":"暴风矩形AOE","MinRadius":"0","MaxRadius":["100"],"Height":"40","RectWidth":"5","AngleRange":"256","AreaRadius":"40","TargetCountLimit":["-1"],"PrepareFrames":["48"],"BrokenRate":"0","BeatBackRate":"0","DamageBase":["29000","47600","61600","729200"],"SkillBaseInfo":{"IdKey":16874,"SkillID":22356,"IconID":13,"Level":0,"Name":"禊祓·绛岚","Desc":"测试技能","Remark":"(22356) 4号_暴风矩形AOE","SpecialDesc":null,"HelpDesc":null,"IsHotkeyExitWhenForget":null,"SimpleDesc":null}},{"Name":"甩尾外功","MinRadius":"0","MaxRadius":["100"],"AngleRange":"128","AreaRadius":"10","TargetCountLimit":["-1"],"PrepareFrames":["32"],"BrokenRate":"0","BeatBackRate":"0","DamageBase":["22600","39400","57000","400","0","0","0","0","0","0"],"SkillBaseInfo":{"IconID":316}},{"Name":"狂暴倒计时","SkillBaseInfo":{"IconID":316}},{"Name":"普攻母技能","MinRadius":"0","MaxRadius":["4"],"DamageBase":["0","0","0","0","0","0","0","0","0","0"],"SkillBaseInfo":{"IconID":316}},{"Name":"甩尾内功","MinRadius":"0","MaxRadius":["100"],"AngleRange":"128","AreaRadius":"10","TargetCountLimit":["-1"],"PrepareFrames":["32"],"BrokenRate":"0","BeatBackRate":"0","DamageBase":["22600","39400","57000","400","0","0","0","0","0","0"],"SkillBaseInfo":{"IconID":316}},{"Name":"符印凛驱散","SkillBaseInfo":{"IconID":316}},{"Name":"阴阳咒印驱散","SkillBaseInfo":{"IconID":316}},{"Name":"甩尾母技能","MinRadius":"0","MaxRadius":["100"],"AngleRange":"128","AreaRadius":"10","TargetCountLimit":["-1"],"PrepareFrames":["32"],"BrokenRate":"0","BeatBackRate":"0","DamageBase":["0","0","0","0","0","0","0","0","0","0"],"SkillBaseInfo":{"IdKey":16879,"SkillID":22362,"IconID":13,"Level":0,"Name":"甩尾","Desc":"测试技能","Remark":"(22362) 4号_式神甩尾母技能","SpecialDesc":null,"HelpDesc":null,"IsHotkeyExitWhenForget":null,"SimpleDesc":null}},{"Name":"阴阳调和","SkillBaseInfo":{"IconID":316}},{"Name":"附身读条","PrepareFrames":["24"],"BrokenRate":"0","BeatBackRate":"0","DamageBase":["0","0","0","0","0","0","0","0","0","0"],"SkillBaseInfo":{"IdKey":16938,"SkillID":22448,"IconID":13,"Level":1,"Name":"凭依","Desc":"测试技能","Remark":"(22448) 4号_附身读条","SpecialDesc":null,"HelpDesc":null,"IsHotkeyExitWhenForget":null,"SimpleDesc":null}},{"Name":"零域读条","PrepareFrames":["144","94"],"BrokenRate":"0","BeatBackRate":"0","DamageBase":["0","0","0","0","0","0","0","0","0","0"],"SkillBaseInfo":{"IdKey":16896,"SkillID":22375,"IconID":13,"Level":1,"Name":"零域","Desc":"测试技能","Remark":"(22375) 4号_零域读条","SpecialDesc":null,"HelpDesc":null,"IsHotkeyExitWhenForget":null,"SimpleDesc":null}},{"Name":"飞扑结束圆形AOE","MinRadius":"0","MaxRadius":["100"],"Height":"40","AngleRange":"256","AreaRadius":"5","TargetCountLimit":["-1"],"DamageBase":["40300","51700","64400","400","0","0","0","0","0","0"],"SkillBaseInfo":{"IdKey":16873,"SkillID":22351,"IconID":13,"Level":0,"Name":"飞扑","Desc":"测试技能","Remark":"(22351) 4号_飞扑结束圆形AOE","SpecialDesc":null,"HelpDesc":null,"IsHotkeyExitWhenForget":null,"SimpleDesc":null}},{"Name":"冰圈AOE","BindBuff":["15665","15665","15665"],"MinRadius":"0","MaxRadius":["100"],"Height":"60","AngleRange":"256","AreaRadius":"5","TargetCountLimit":["-1"],"DamageBase":["0","0","0","0","0","6","7","8","9","9"],"BindBuffDetail":[{"IdKey":13709,"BuffID":15665,"IconID":3444,"Level":1,"Name":"咒术抗性","Desc":"在尹青羲的协助下，能够抵御特定的低级咒术","Remark":"(15665)(1)4号_抵御咒术"},{"IdKey":13709,"BuffID":15665,"IconID":3444,"Level":1,"Name":"咒术抗性","Desc":"在尹青羲的协助下，能够抵御特定的低级咒术","Remark":"(15665)(1)4号_抵御咒术"},{"IdKey":13709,"BuffID":15665,"IconID":3444,"Level":1,"Name":"咒术抗性","Desc":"在尹青羲的协助下，能够抵御特定的低级咒术","Remark":"(15665)(1)4号_抵御咒术"}],"SkillBaseInfo":{"IdKey":17086,"SkillID":22645,"IconID":13,"Level":0,"Name":"咒印冰寒","Desc":"测试技能","Remark":"(22645) 4号_冰圈AOE","SpecialDesc":null,"HelpDesc":null,"IsHotkeyExitWhenForget":null,"SimpleDesc":null}},{"Name":"禊祓岚吟","AddSlowCheckDestBuff":"15665","BindBuff":["16187"],"MinRadius":"0","MaxRadius":["100"],"Height":"100","AngleRange":"256","AreaRadius":"100","TargetCountLimit":["-1"],"DamageBase":["28300","35300","42400","49200","57400","410100","55200","64400","459800","0"],"Immune":["360","6301","856","203","2797","10486","9830","13771"],"BindBuffDetail":[],"ImmuneDetail":[{"IdKey":367,"BuffID":360,"IconID":1456,"Level":0,"Name":"御","Desc":"每层化解一次伤害","Remark":"(360)(0)天策-御"},{"IdKey":6631,"BuffID":6301,"IconID":3823,"Level":1,"Name":"纵遇善缘","Desc":"每层化解一次伤害","Remark":"(6301)(1)明教_生死劫格挡"},{"IdKey":1032,"BuffID":856,"IconID":421,"Level":1,"Name":"健骨","Desc":"免疫一切内功伤害","Remark":"(856)(1)锻骨诀内功无敌效果"},{"IdKey":146,"BuffID":203,"IconID":1457,"Level":1,"Name":"啸如虎","Desc":"受到疗伤成效提高2%，不会重伤","Remark":"(203)(1)天策-啸如虎-傲血战意"},{"IdKey":3282,"BuffID":2797,"IconID":432,"Level":0,"Name":"罗汉金身","Desc":"伤害反弹30%，自身伤害40%转化为内力值","Remark":"(2797)(0)罗汉金身+30%段3"},{"IdKey":9830,"BuffID":10486,"IconID":422,"Level":1,"Name":"无相诀","Desc":"反弹受到的伤害70%","Remark":"(10486)(1)无相减伤效果降低"},{"IdKey":9447,"BuffID":9830,"IconID":430,"Level":1,"Name":"舍生","Desc":"受到伤害的99%转移给少林","Remark":"(9830)(1)大狮子吼承伤"},{"IdKey":12280,"BuffID":13771,"IconID":10637,"Level":1,"Name":"疾电叱羽","Desc":"海雕承担受到的伤害","Remark":"(13771)(1)叱电叱羽承伤实际效果"}],"SkillBaseInfo":{"IdKey":16882,"SkillID":22365,"IconID":13,"Level":0,"Name":"禊祓岚吟","Desc":"测试技能","Remark":"(22365) 4号_禊祓岚吟","SpecialDesc":null,"HelpDesc":null,"IsHotkeyExitWhenForget":null,"SimpleDesc":null}},{"Name":"引力黑洞内圈伤害","BindBuff":["15916"],"MinRadius":"0","MaxRadius":["100"],"Height":"60","AngleRange":"256","AreaRadius":"10","TargetCountLimit":["-1"],"DamageBase":["4100","5700","12900","4","5","6","7","8","9"],"Immune":["360","6301","856","203","2797","10486","9830","13771"],"BindBuffDetail":[{"IdKey":13889,"BuffID":15916,"IconID":10484,"Level":1,"Name":"强大引力","Desc":"强大的吸引力将你控制，移动速度大幅下降","Remark":"(15916)(1)4号_天地剧变减速"}],"ImmuneDetail":[{"IdKey":367,"BuffID":360,"IconID":1456,"Level":0,"Name":"御","Desc":"每层化解一次伤害","Remark":"(360)(0)天策-御"},{"IdKey":6631,"BuffID":6301,"IconID":3823,"Level":1,"Name":"纵遇善缘","Desc":"每层化解一次伤害","Remark":"(6301)(1)明教_生死劫格挡"},{"IdKey":1032,"BuffID":856,"IconID":421,"Level":1,"Name":"健骨","Desc":"免疫一切内功伤害","Remark":"(856)(1)锻骨诀内功无敌效果"},{"IdKey":146,"BuffID":203,"IconID":1457,"Level":1,"Name":"啸如虎","Desc":"受到疗伤成效提高2%，不会重伤","Remark":"(203)(1)天策-啸如虎-傲血战意"},{"IdKey":3282,"BuffID":2797,"IconID":432,"Level":0,"Name":"罗汉金身","Desc":"伤害反弹30%，自身伤害40%转化为内力值","Remark":"(2797)(0)罗汉金身+30%段3"},{"IdKey":9830,"BuffID":10486,"IconID":422,"Level":1,"Name":"无相诀","Desc":"反弹受到的伤害70%","Remark":"(10486)(1)无相减伤效果降低"},{"IdKey":9447,"BuffID":9830,"IconID":430,"Level":1,"Name":"舍生","Desc":"受到伤害的99%转移给少林","Remark":"(9830)(1)大狮子吼承伤"},{"IdKey":12280,"BuffID":13771,"IconID":10637,"Level":1,"Name":"疾电叱羽","Desc":"海雕承担受到的伤害","Remark":"(13771)(1)叱电叱羽承伤实际效果"}],"SkillBaseInfo":{"IdKey":16911,"SkillID":22400,"IconID":13,"Level":0,"Name":"天地剧变","Desc":"测试技能","Remark":"(22400) 4号_引力黑洞内圈伤害","SpecialDesc":null,"HelpDesc":null,"IsHotkeyExitWhenForget":null,"SimpleDesc":null}},{"Name":"零域","BindBuff":["16186"],"MinRadius":"0","MaxRadius":["100"],"Height":"60","AngleRange":"256","AreaRadius":"8","TargetCountLimit":["-1"],"DamageBase":["21200","38900","49500","24600","45100","57400","27600","50600","64400"],"Immune":["360","6301","856","203","2797","10486","9830","13771"],"BindBuffDetail":[],"ImmuneDetail":[{"IdKey":367,"BuffID":360,"IconID":1456,"Level":0,"Name":"御","Desc":"每层化解一次伤害","Remark":"(360)(0)天策-御"},{"IdKey":6631,"BuffID":6301,"IconID":3823,"Level":1,"Name":"纵遇善缘","Desc":"每层化解一次伤害","Remark":"(6301)(1)明教_生死劫格挡"},{"IdKey":1032,"BuffID":856,"IconID":421,"Level":1,"Name":"健骨","Desc":"免疫一切内功伤害","Remark":"(856)(1)锻骨诀内功无敌效果"},{"IdKey":146,"BuffID":203,"IconID":1457,"Level":1,"Name":"啸如虎","Desc":"受到疗伤成效提高2%，不会重伤","Remark":"(203)(1)天策-啸如虎-傲血战意"},{"IdKey":3282,"BuffID":2797,"IconID":432,"Level":0,"Name":"罗汉金身","Desc":"伤害反弹30%，自身伤害40%转化为内力值","Remark":"(2797)(0)罗汉金身+30%段3"},{"IdKey":9830,"BuffID":10486,"IconID":422,"Level":1,"Name":"无相诀","Desc":"反弹受到的伤害70%","Remark":"(10486)(1)无相减伤效果降低"},{"IdKey":9447,"BuffID":9830,"IconID":430,"Level":1,"Name":"舍生","Desc":"受到伤害的99%转移给少林","Remark":"(9830)(1)大狮子吼承伤"},{"IdKey":12280,"BuffID":13771,"IconID":10637,"Level":1,"Name":"疾电叱羽","Desc":"海雕承担受到的伤害","Remark":"(13771)(1)叱电叱羽承伤实际效果"}],"SkillBaseInfo":{"IdKey":16894,"SkillID":22374,"IconID":13,"Level":0,"Name":"零域","Desc":"测试技能","Remark":"(22374) 4号_零域","SpecialDesc":null,"HelpDesc":null,"IsHotkeyExitWhenForget":null,"SimpleDesc":null}},{"Name":"引力黑洞外围伤害","MinRadius":"0","MaxRadius":["100"],"Height":"60","ProtectRadius":"9","AngleRange":"256","AreaRadius":"150","TargetCountLimit":["-1"],"DamageBase":["1800","2100","2300","4","5","6","7","8","9"],"Immune":["360","6301","856","203","2797","10486","9830","13771"],"ImmuneDetail":[{"IdKey":367,"BuffID":360,"IconID":1456,"Level":0,"Name":"御","Desc":"每层化解一次伤害","Remark":"(360)(0)天策-御"},{"IdKey":6631,"BuffID":6301,"IconID":3823,"Level":1,"Name":"纵遇善缘","Desc":"每层化解一次伤害","Remark":"(6301)(1)明教_生死劫格挡"},{"IdKey":1032,"BuffID":856,"IconID":421,"Level":1,"Name":"健骨","Desc":"免疫一切内功伤害","Remark":"(856)(1)锻骨诀内功无敌效果"},{"IdKey":146,"BuffID":203,"IconID":1457,"Level":1,"Name":"啸如虎","Desc":"受到疗伤成效提高2%，不会重伤","Remark":"(203)(1)天策-啸如虎-傲血战意"},{"IdKey":3282,"BuffID":2797,"IconID":432,"Level":0,"Name":"罗汉金身","Desc":"伤害反弹30%，自身伤害40%转化为内力值","Remark":"(2797)(0)罗汉金身+30%段3"},{"IdKey":9830,"BuffID":10486,"IconID":422,"Level":1,"Name":"无相诀","Desc":"反弹受到的伤害70%","Remark":"(10486)(1)无相减伤效果降低"},{"IdKey":9447,"BuffID":9830,"IconID":430,"Level":1,"Name":"舍生","Desc":"受到伤害的99%转移给少林","Remark":"(9830)(1)大狮子吼承伤"},{"IdKey":12280,"BuffID":13771,"IconID":10637,"Level":1,"Name":"疾电叱羽","Desc":"海雕承担受到的伤害","Remark":"(13771)(1)叱电叱羽承伤实际效果"}],"SkillBaseInfo":{"IdKey":16910,"SkillID":22399,"IconID":13,"Level":0,"Name":"天地剧变","Desc":"测试技能","Remark":"(22399) 4号_引力黑洞外围伤害","SpecialDesc":null,"HelpDesc":null,"IsHotkeyExitWhenForget":null,"SimpleDesc":null}},{"Name":"禊祓零域","MinRadius":"0","MaxRadius":["100"],"Height":"60","AngleRange":"256","AreaRadius":"100","TargetCountLimit":["-1"],"DamageBase":["17700","20500","25700","4","5","6","7","8","9"],"Immune":["360","6301","856","203","2797","10486","9830","13771"],"ImmuneDetail":[{"IdKey":367,"BuffID":360,"IconID":1456,"Level":0,"Name":"御","Desc":"每层化解一次伤害","Remark":"(360)(0)天策-御"},{"IdKey":6631,"BuffID":6301,"IconID":3823,"Level":1,"Name":"纵遇善缘","Desc":"每层化解一次伤害","Remark":"(6301)(1)明教_生死劫格挡"},{"IdKey":1032,"BuffID":856,"IconID":421,"Level":1,"Name":"健骨","Desc":"免疫一切内功伤害","Remark":"(856)(1)锻骨诀内功无敌效果"},{"IdKey":146,"BuffID":203,"IconID":1457,"Level":1,"Name":"啸如虎","Desc":"受到疗伤成效提高2%，不会重伤","Remark":"(203)(1)天策-啸如虎-傲血战意"},{"IdKey":3282,"BuffID":2797,"IconID":432,"Level":0,"Name":"罗汉金身","Desc":"伤害反弹30%，自身伤害40%转化为内力值","Remark":"(2797)(0)罗汉金身+30%段3"},{"IdKey":9830,"BuffID":10486,"IconID":422,"Level":1,"Name":"无相诀","Desc":"反弹受到的伤害70%","Remark":"(10486)(1)无相减伤效果降低"},{"IdKey":9447,"BuffID":9830,"IconID":430,"Level":1,"Name":"舍生","Desc":"受到伤害的99%转移给少林","Remark":"(9830)(1)大狮子吼承伤"},{"IdKey":12280,"BuffID":13771,"IconID":10637,"Level":1,"Name":"疾电叱羽","Desc":"海雕承担受到的伤害","Remark":"(13771)(1)叱电叱羽承伤实际效果"}],"SkillBaseInfo":{"IdKey":16898,"SkillID":22378,"IconID":13,"Level":0,"Name":"禊祓·零域","Desc":"测试技能","Remark":"(22378) 4号_禊祓零域","SpecialDesc":null,"HelpDesc":null,"IsHotkeyExitWhenForget":null,"SimpleDesc":null}}]}